barz/__init__.py
barz/__main__.py
barz/py.typed
barz-0.1.0.dist-info/WHEEL
barz-0.1.0.dist-info/entry_points.txt
barz-0.1.0.dist-info/METADATA
barz-0.1.0.dist-info/RECORD
