Metadata-Version: 2.3
Name: barz
Version: 0.1.0
Summary: Bar charts in the terminal
Author: Zeev Rotshtein
Author-email: Zeev Rotshtein <zeevro@gmail.com>
Requires-Python: >=3.10
Project-URL: Repository, https://github.com/zeevro/barz
